pqr/__init__.py
pqr/users.py
pqr/xyz/__init__.py
pqr/xyz/math.py
new_pqr_packages-1.2.dist-info/METADATA
new_pqr_packages-1.2.dist-info/WHEEL
new_pqr_packages-1.2.dist-info/top_level.txt
new_pqr_packages-1.2.dist-info/RECORD
