Metadata-Version: 2.1
Name: new-pqr-packages
Version: 1.2
Summary: This Package is custom package with some functions
Author: beauty
Author-email: banamika5@gmail.com
